caikit_nlp/__init__.py
caikit_nlp/_version.py
caikit_nlp/version.py
caikit_nlp/config/__init__.py
caikit_nlp/config/config.yml
caikit_nlp/data_model/__init__.py
caikit_nlp/data_model/generation.py
caikit_nlp/model_management/__init__.py
caikit_nlp/model_management/tgis_auto_finder.py
caikit_nlp/modules/__init__.py
caikit_nlp/modules/text_classification/__init__.py
caikit_nlp/modules/text_classification/sequence_classification.py
caikit_nlp/modules/text_embedding/__init__.py
caikit_nlp/modules/text_embedding/crossencoder.py
caikit_nlp/modules/text_embedding/embedding.py
caikit_nlp/modules/text_embedding/utils.py
caikit_nlp/modules/text_generation/__init__.py
caikit_nlp/modules/text_generation/peft_config.py
caikit_nlp/modules/text_generation/peft_prompt_tuning.py
caikit_nlp/modules/text_generation/peft_tgis_remote.py
caikit_nlp/modules/text_generation/text_generation_local.py
caikit_nlp/modules/text_generation/text_generation_tgis.py
caikit_nlp/modules/token_classification/__init__.py
caikit_nlp/modules/token_classification/filtered_span_classification.py
caikit_nlp/modules/tokenization/__init__.py
caikit_nlp/modules/tokenization/regex_sentence_splitter.py
caikit_nlp/resources/__init__.py
caikit_nlp/resources/pretrained_model/__init__.py
caikit_nlp/resources/pretrained_model/base.py
caikit_nlp/resources/pretrained_model/hf_auto_causal_lm.py
caikit_nlp/resources/pretrained_model/hf_auto_seq2seq_lm.py
caikit_nlp/resources/pretrained_model/hf_auto_seq_classifier.py
caikit_nlp/toolkit/__init__.py
caikit_nlp/toolkit/data_stream_wrapper.py
caikit_nlp/toolkit/data_type_utils.py
caikit_nlp/toolkit/task_specific_utils.py
caikit_nlp/toolkit/torch_run.py
caikit_nlp/toolkit/trainer_utils.py
caikit_nlp/toolkit/verbalizer_utils.py
caikit_nlp/toolkit/text_generation/__init__.py
caikit_nlp/toolkit/text_generation/model_run_utils.py
caikit_nlp/toolkit/text_generation/tgis_utils.py
caikit_nlp-0.5.15.dist-info/licenses/LICENSE
caikit_nlp-0.5.15.dist-info/METADATA
caikit_nlp-0.5.15.dist-info/WHEEL
caikit_nlp-0.5.15.dist-info/top_level.txt
caikit_nlp-0.5.15.dist-info/RECORD
