Metadata-Version: 2.4
Name: caikit-nlp
Version: 0.5.15
Summary: Caikit NLP
License: Apache-2.0
Project-URL: Source, https://github.com/caikit/caikit-nlp
Classifier: License :: OSI Approved :: Apache Software License
Requires-Python: ~=3.9
License-File: LICENSE
Requires-Dist: caikit[runtime-grpc,runtime-http]<0.29.0,>=0.26.34
Requires-Dist: caikit-tgis-backend<0.2.0,>=0.1.36
Requires-Dist: grpcio>=1.62.2
Requires-Dist: grpcio-reflection>=1.62.2
Requires-Dist: grpcio-health-checking>=1.62.2
Requires-Dist: accelerate>=1.3.0
Requires-Dist: datasets>=3.3.0
Requires-Dist: huggingface-hub
Requires-Dist: numpy<2,>=1.23.0
Requires-Dist: pandas>=2.2.3
Requires-Dist: scikit-learn>=1.6.1
Requires-Dist: scipy>=1.10.0
Requires-Dist: sentence-transformers<3.5.0,>=3.4.0
Requires-Dist: tokenizers>=0.20.0
Requires-Dist: torch<2.9.0,>=2.3.1
Requires-Dist: tqdm>=4.67.0
Requires-Dist: transformers<4.50.0,>=4.48.3
Requires-Dist: peft==0.14.0
Dynamic: license-file
